flask_selfheal/__init__.py
flask_selfheal/resolvers.py
flask_selfheal/selfheal.py
flask_selfheal-1.1.1.dist-info/METADATA
flask_selfheal-1.1.1.dist-info/WHEEL
flask_selfheal-1.1.1.dist-info/licenses/LICENSE
flask_selfheal-1.1.1.dist-info/RECORD
