Metadata-Version: 2.4
Name: flask-selfheal
Version: 1.1.1
Summary: Self-healing URLs for Flask applications with intelligent resolvers
Project-URL: Homepage, https://github.com/GovernmentPlates/flask-selfheal
Project-URL: Repository, https://github.com/GovernmentPlates/flask-selfheal.git
Project-URL: Issues, https://github.com/GovernmentPlates/flask-selfheal/issues
Project-URL: Documentation, https://github.com/GovernmentPlates/flask-selfheal#readme
Author-email: "Dominic H." <dom@dominic.sk>
License: MIT License
License-File: LICENSE
Keywords: flask,fuzzy-matching,routing,self-healing,url,web
Classifier: Framework :: Flask
Classifier: License :: OSI Approved :: MIT License
Classifier: Natural Language :: English
Requires-Python: >=3.13
Requires-Dist: flask-sqlalchemy>=3.1
Requires-Dist: flask>=3.1
